{
  "session_id": "FF-TRAIN-0007",
  "firefighter_id": "FF_BASIS_02",
  "firefighter_user": "KZIELINSKA",
  "controller": "MCONTROL",
  "system": "PRD-ECC",
  "client": "ACME-DE",
  "transaction_log": [
    {
      "timestamp": "2026-04-19T07:04:56Z",
      "tcode": "SU53",
      "description": "Display Authorization Check"
    },
    {
      "timestamp": "2026-04-19T07:06:39Z",
      "tcode": "SM12",
      "description": "Lock Entries"
    },
    {
      "timestamp": "2026-04-19T07:08:39Z",
      "tcode": "SM50",
      "description": "Process Overview"
    },
    {
      "timestamp": "2026-04-19T07:10:28Z",
      "tcode": "SM37",
      "description": "Job Overview"
    },
    {
      "timestamp": "2026-04-19T07:11:40Z",
      "tcode": "SM12",
      "description": "Lock Entries"
    },
    {
      "timestamp": "2026-04-19T07:12:42Z",
      "tcode": "SESSION_MANAGER",
      "description": "Session Manager"
    }
  ],
  "change_log": [],
  "system_log": [],
  "os_command_log": [],
  "start_time": "2026-04-19T07:04:44Z",
  "end_time": "2026-04-19T07:13:44Z",
  "reason_code": "Investigated SM12 lock entries blocking month-end close per PRB0045806; identified orphaned lock from killed batch job, no manual unlock needed; documented findings.",
  "ticket_reference": "PRB0045806"
}